README.md
setup.py
dream_apo.egg-info/PKG-INFO
dream_apo.egg-info/SOURCES.txt
dream_apo.egg-info/dependency_links.txt
dream_apo.egg-info/not-zip-safe
dream_apo.egg-info/requires.txt
dream_apo.egg-info/top_level.txt
dreamapi/__init__.py
dreamapi/texttospeech/__init__.py
dreamapi/texttospeech/tts.py
dreamapi/utils/__init__.py
dreamapi/utils/synthesis.py
dreamapi/utils/upload.py
dreamapi/utils/utils.py
dreamapi/videogenerator/__init__.py
dreamapi/videogenerator/video_generator.py