Metadata-Version: 2.1
Name: dream-apo
Version: 0.0.2
Summary: DreamApi
Home-page: https://github.com/DreamFaceAI/dream_api
Author: DreamApi
License: MIT
Classifier: Programming Language :: Python :: 3
Classifier: License :: OSI Approved :: MIT License
Classifier: Operating System :: OS Independent
Requires-Python: >=3.6
Requires-Dist: requests
